SalamHunter/SalamHunter.py
SalamHunter/__init__.py
SalamHunter-0.0.16.dist-info/LICENSE
SalamHunter-0.0.16.dist-info/METADATA
SalamHunter-0.0.16.dist-info/WHEEL
SalamHunter-0.0.16.dist-info/top_level.txt
SalamHunter-0.0.16.dist-info/RECORD
