Metadata-Version: 2.1
Name: SalamHunter
Version: 0.0.16
Summary: • Script Very Nice To Helping Programmer .
Home-page: https://github.com/salammzere3/SalamHunterr
Author: salammzere3
Author-email: salamhunter@gmail.com
Project-URL: Bug Tracker, https://github.com/pypa/sampleproject/issues
Classifier: Programming Language :: Python :: 3
Classifier: Programming Language :: Python :: 2
Classifier: License :: OSI Approved :: MIT License
Classifier: Operating System :: OS Independent
Requires-Python: >=3
License-File: LICENSE
